.coveragerc
.editorconfig
.gitignore
.travis.yml
CHANGELOG.md
LICENSE
MANIFEST.in
PKG-INFO
README.rst
RESOURCES.md
requirements.txt
setup.cfg
setup.py
tox.ini
.travis/semver.sh
ci/bootstrap.py
src/.gitignore
src/mbizmomo/__init__.py
src/mbizmomo/__main__.py
src/mbizmomo/cli.py
src/mbizmomo/client.py
src/mbizmomo/collection.py
src/mbizmomo/config.py
src/mbizmomo/disbursement.py
src/mbizmomo/errors.py
src/mbizmomo/remittance.py
src/mbizmomo/utils.py
src/mbizmomo.egg-info/PKG-INFO
src/mbizmomo.egg-info/SOURCES.txt
src/mbizmomo.egg-info/dependency_links.txt
src/mbizmomo.egg-info/entry_points.txt
src/mbizmomo.egg-info/not-zip-safe
src/mbizmomo.egg-info/requires.txt
src/mbizmomo.egg-info/top_level.txt
tests/__init__.py
tests/integration/test_collection.py
tests/integration/test_disbursement.py
tests/integration/test_remittance.py
tests/integration/test_sandbox.py
tests/integration/features/collections.feature
tests/integration/features/disbursements.feature
tests/integration/features/remittances.feature
tests/integration/features/sandbox.feature
tests/unitests/__init__.py
tests/unitests/test_collection.py
tests/unitests/test_disbursement.py
tests/unitests/test_remittance.py
tests/unitests/utils.py